mind_castle/__init__.py
mind_castle/__main__.py
mind_castle/exceptions.py
mind_castle/secret_store_base.py
mind_castle/sqlalchemy_type.py
mind_castle/stores/__init__.py
mind_castle/stores/aws_kms.py
mind_castle/stores/aws_secrets_manager.py
mind_castle/stores/json_store.py
mind_castle/stores/local_encryption.py
mind_castle/stores/memory.py
mind_castle/migration_tool.py
mind_castle-0.4.6.dist-info/METADATA
mind_castle-0.4.6.dist-info/WHEEL
mind_castle-0.4.6.dist-info/licenses/LICENSE
mind_castle-0.4.6.dist-info/RECORD
