Metadata-Version: 2.4
Name: mind-castle
Version: 0.4.6
Summary: A universal secrets manager
License-File: LICENSE
Requires-Python: >=3.9
Requires-Dist: boto3
Requires-Dist: hvac
Requires-Dist: hypothesis-jsonschema>=0.23.1
Requires-Dist: iterfzf>=1.4.0.54.3
Requires-Dist: pydantic>=2.11.4
Requires-Dist: rich>=13.9.4
Requires-Dist: sqlalchemy<3.0.0,>=2.0.0
Requires-Dist: typer>=0.12.5
Requires-Dist: wrapt>=1.17.2
